Metadata-Version: 1.0
Name: multiwrapper
Version: 0.1.1
Summary: easy to use multiprocessing
Home-page: https://github.com/sdorkenw/MultiWrapper.git
Author: Sven Dorkenwald
Author-email: svenmd@princeton.edu
License: UNKNOWN
Platform: UNKNOWN
